{
  "ModelName": "Skran Visitor BFF",
  "ModelMetadata": {
    "Author": "Hugh",
    "DateCreated": "Jan 07, 2023, 04:29 PM",
    "DateLastModified": "Jan 14, 2023, 03:32 PM",
    "Description": "Table design backing REST API for Skran recipes site",
    "AWSService": "Amazon DynamoDB",
    "Version": "3.0"
  },
  "DataModel": [
    {
      "TableName": "DeployStage-SkranVisitorBff-SkranVisitorBffVisitorBffTable5DD409E6-10C5BXR759OQK",
      "KeyAttributes": {
        "PartitionKey": {
          "AttributeName": "Primary",
          "AttributeType": "S"
        },
        "SortKey": {
          "AttributeName": "Sort",
          "AttributeType": "S"
        }
      },
      "NonKeyAttributes": [
        {
          "AttributeName": "Id",
            "AttributeType": "S"
        },
        {
          "AttributeName": "Type",
          "AttributeType": "S"
        },
        {
          "AttributeName": "Components",
          "AttributeType": "L"
        },
        {
          "AttributeName": "Time",
          "AttributeType": "N"
        },
        {
          "AttributeName": "Instructions",
          "AttributeType": "S"
        },
        {
          "AttributeName": "Recipes",
          "AttributeType": "SS"
        },
        {
          "AttributeName": "Title",
          "AttributeType": "S"
        }
      ],
      "TableData": [
        {
          "Primary": {
            "S": "RECIPE#1234"
          },
          "Sort": {
            "S": "TITLE#SPAGHETTI_BOLOGNESE"
          },
          "Type": {
            "S": "RECIPE"
          },
          "Id": {
            "S": "1234"
          },
          "Title": {
            "S": "Spaghetti Bolognese"
          },
          "Components": {
            "L": [
              {
                "M": {
                  "Title": {
                    "S": "Pasta"
                  },
                  "Ingredients": {
                    "L": [
                      {
                        "M": {
                          "Title": {
                            "S": "Pasta"
                          },
                          "Value": {
                            "N": "500"
                          },
                          "Measurement": {
                            "S": "grams"
                          }
                        }
                      }
                    ]
                  }
                }
              },
              {
                "M": {
                  "Title": {
                    "S": "Sauce"
                  },
                  "Ingredients": {
                    "L": [
                      {
                        "M": {
                          "Title": {
                            "S": "Beef Mince"
                          },
                          "Value": {
                            "N": "250"
                          },
                          "Measurement": {
                            "S": "grams"
                          }
                        }
                      },
                      {
                        "M": {
                          "Title": {
                            "S": "Tinned Tomatoes"
                          },
                          "Value": {
                            "N": "500"
                          },
                          "Measurement": {
                            "S": "grams"
                          }
                        }
                      },
                      {
                        "M": {
                          "Title": {
                            "S": "Garlic"
                          },
                          "Value": {
                            "N": "50"
                          },
                          "Measurement": {
                            "S": "grams"
                          }
                        }
                      }
                    ]
                  }
                }
              }
            ]
          },
          "Time": {
            "N": "30"
          },
          "Instructions": {
            "S": "Cook pasta for 15 minutes."
          }
        },
        {
          "Primary": {
            "S": "SEARCH"
          },
          "Sort": {
            "S": "BEEF_MINCE"
          },
          "Title": {
            "S": "Beef Mince"
          },
          "Type": {
            "S": "SEARCH"
          },
          "Recipes": {
            "SS": [
              "1234",
              "5678"
            ]
          }
        },
        {
          "Primary": {
            "S": "SEARCH"
          },
          "Sort": {
            "S": "GARLIC"
          },
          "Title": {
            "S": "Garlic"
          },
          "Type": {
            "S": "SEARCH"
          },
          "Recipes": {
            "SS": [
              "1234",
              "5678"
            ]
          }
        },
        {
          "Primary": {
            "S": "SEARCH"
          },
          "Sort": {
            "S": "PASTA"
          },
          "Type": {
            "S": "SEARCH"
          },
          "Title": {
            "S": "Pasta"
          },
          "Recipes": {
            "SS": [
              "1234",
              "5678"
            ]
          }
        },
        {
          "Primary": {
            "S": "SEARCH"
          },
          "Sort": {
            "S": "TINNED_TOMATOES"
          },
          "Type": {
            "S": "SEARCH"
          },
          "Title": {
            "S": "Tinned Tomatoes"
          },
          "Recipes": {
            "SS": [
              "1234",
              "5678"
            ]
          }
        }
      ],
      "DataAccess": {
        "MySql": {}
      },
      "BillingMode": "PROVISIONED",
      "ProvisionedCapacitySettings": {
        "ProvisionedThroughput": {
          "ReadCapacityUnits": 5,
          "WriteCapacityUnits": 5
        },
        "AutoScalingRead": {
          "ScalableTargetRequest": {
            "MinCapacity": 1,
            "MaxCapacity": 25,
            "ServiceRole": "AWSServiceRoleForApplicationAutoScaling_DynamoDBTable"
          },
          "ScalingPolicyConfiguration": {
            "TargetValue": 75
          }
        },
        "AutoScalingWrite": {
          "ScalableTargetRequest": {
            "MinCapacity": 1,
            "MaxCapacity": 25,
            "ServiceRole": "AWSServiceRoleForApplicationAutoScaling_DynamoDBTable"
          },
          "ScalingPolicyConfiguration": {
            "TargetValue": 75
          }
        }
      }
    }
  ]
}
