{
  "SkranAppTable": [
    {
      "PutRequest": {
        "Item": {
          "Primary": {
            "S": "RECIPE#1234"
          },
          "Sort": {
            "S": "TITLE#SPAGHETTI_BOLOGNESE"
          },
          "Type": {
            "S": "RECIPE"
          },
          "Id": {
            "N": "1234"
          },
          "Title": {
            "S": "Spaghetti Bolognese"
          },
          "Components": {
            "L": [
              {
                "M": {
                  "Title": {
                    "S": "Pasta"
                  },
                  "Ingredients": {
                    "L": [
                      {
                        "M": {
                          "Title": {
                            "S": "Pasta"
                          },
                          "Value": {
                            "N": "500"
                          },
                          "Measurement": {
                            "S": "grams"
                          }
                        }
                      }
                    ]
                  }
                }
              },
              {
                "M": {
                  "Title": {
                    "S": "Sauce"
                  },
                  "Ingredients": {
                    "L": [
                      {
                        "M": {
                          "Title": {
                            "S": "Beef Mince"
                          },
                          "Value": {
                            "N": "250"
                          },
                          "Measurement": {
                            "S": "grams"
                          }
                        }
                      },
                      {
                        "M": {
                          "Title": {
                            "S": "Tinned Tomatoes"
                          },
                          "Value": {
                            "N": "500"
                          },
                          "Measurement": {
                            "S": "grams"
                          }
                        }
                      },
                      {
                        "M": {
                          "Title": {
                            "S": "Garlic"
                          },
                          "Value": {
                            "N": "50"
                          },
                          "Measurement": {
                            "S": "grams"
                          }
                        }
                      }
                    ]
                  }
                }
              }
            ]
          },
          "Time": {
            "N": "30"
          },
          "Instructions": {
            "S": "Cook pasta for 15 minutes."
          }
        }
      }
    },
    {
      "PutRequest": {
        "Item": {
          "Primary": {
            "S": "RECIPE#5678"
          },
          "Sort": {
            "S": "TITLE#CHICKEN_CURRY"
          },
          "Type": {
            "S": "RECIPE"
          },
          "Id": {
            "N": "5678"
          },
          "Title": {
            "S": "Chicken Curry"
          },
          "Components": {
            "L": [
              {
                "M": {
                  "Title": {
                    "S": "Rice"
                  },
                  "Ingredients": {
                    "L": [
                      {
                        "M": {
                          "Title": {
                            "S": "Rice"
                          },
                          "Value": {
                            "N": "500"
                          },
                          "Measurement": {
                            "S": "g"
                          }
                        }
                      }
                    ]
                  }
                }
              },
              {
                "M": {
                  "Title": {
                    "S": "Gravy"
                  },
                  "Ingredients": {
                    "L": [
                      {
                        "M": {
                          "Title": {
                            "S": "Onions"
                          },
                          "Value": {
                            "N": "500"
                          },
                          "Measurement": {
                            "S": "g"
                          }
                        }
                      },
                      {
                        "M": {
                          "Title": {
                            "S": "Garlic"
                          },
                          "Value": {
                            "N": "2"
                          },
                          "Measurement": {
                            "S": "Tbsp"
                          }
                        }
                      },
                      {
                        "M": {
                          "Title": {
                            "S": "Tomatoes"
                          },
                          "Value": {
                            "N": "500"
                          },
                          "Measurement": {
                            "S": "g"
                          }
                        }
                      },
                      {
                        "M": {
                          "Title": {
                            "S": "Cumin"
                          },
                          "Value": {
                            "N": "1"
                          },
                          "Measurement": {
                            "S": "Tsp"
                          }
                        }
                      }
                    ]
                  }
                }
              }
            ]
          },
          "Time": {
            "N": "30"
          },
          "Instructions": {
            "S": "Cook pasta for 15 minutes."
          }
        }
      }
    },
    {
      "PutRequest": {
        "Item": {
          "Primary": {
            "S": "SEARCH#BEEF_MINCE"
          },
          "Sort": {
            "S": "BEEF_MINCE"
          },
          "Type": {
            "S": "SEARCH"
          },
          "Title": {
            "S": "Beef Mince"
          },
          "Recipes": {
            "SS": [
              "1234",
              "5678"
            ]
          }
        }
      }
    },
    {
      "PutRequest": {
        "Item": {
          "Primary": {
            "S": "SEARCH#GARLIC"
          },
          "Sort": {
            "S": "GARLIC"
          },
          "Type": {
            "S": "SEARCH"
          },
          "Title": {
            "S": "Garlic"
          },
          "Recipes": {
            "SS": [
              "1234",
              "5678"
            ]
          }
        }
      }
    },
    {
      "PutRequest": {
        "Item": {
          "Primary": {
            "S": "SEARCH#PASTA"
          },
          "Sort": {
            "S": "PASTA"
          },
          "Type": {
            "S": "SEARCH"
          },
          "Title": {
            "S": "Pasta"
          },
          "Recipes": {
            "SS": [
              "1234",
              "5678"
            ]
          }
        }
      }
    },
    {
      "PutRequest": {
        "Item": {
          "Primary": {
            "S": "SEARCH#TINNED_TOMATOES"
          },
          "Sort": {
            "S": "TINNED_TOMATOES"
          },
          "Type": {
            "S": "SEARCH"
          },
          "Title": {
            "S": "Tinned Tomatoes"
          },
          "Recipes": {
            "SS": [
              "1234",
              "5678"
            ]
          }
        }
      }
    }
  ]
}